[[-1744092680, "{\"displayProperties\":{\"description\":\"Devrim Kay stands watch in the EDZ, protecting the small group of people who now call the Farm their home.\",\"name\":\"Clan Steward\",\"icon\":\"/common/destiny2_content/icons/0403dd7de992e8e362764d6f7c24a36e.png\",\"hasIcon\":true},\"progressionHash\":0,\"rewardItemHash\":0,\"rewardVendorHash\":0,\"hash\":2550874616,\"index\":3,\"redacted\":false}"], [-1368334461, "{\"displayProperties\":{\"description\":\"Cayde-6 is the Hunter representative of the Vanguard, but most of his dealings are a bit less... official.\",\"name\":\"Vanguard Scout\",\"icon\":\"/common/destiny2_content/icons/cd6a4764552ad94823007262146fd351.png\",\"hasIcon\":true},\"progressionHash\":0,\"rewardItemHash\":0,\"rewardVendorHash\":0,\"hash\":2926632835,\"index\":23,\"redacted\":false}"], [-1063194257, "{\"displayProperties\":{\"description\":\"Ikora Rey oversees the Vanguard's research and intelligence operations. Guardians and scholars seek her mentorship from far and wide.\",\"name\":\"Vanguard Research\",\"icon\":\"/common/destiny2_content/icons/f7c18254609ea4081fd411835ef111f7.png\",\"hasIcon\":true},\"progressionHash\":3231773039,\"tokenValues\":{\"3957264072\":1000},\"rewardItemHash\":1353730260,\"rewardVendorHash\":1353730260,\"vendors\":[{\"vendorHash\":1976548992,\"destinationHash\":4188263703,\"backgroundImagePath\":\"img/destiny_content/factions/vendors/farm-meditations-ikora-0.jpg\"},{\"vendorHash\":1976548992,\"destinationHash\":333456177,\"backgroundImagePath\":\"img/destiny_content/factions/vendors/meditations-ikora-rey.jpg\"}],\"hash\":3231773039,\"index\":13,\"redacted\":false}"], [-896916254, "{\"displayProperties\":{\"description\":\"Dead Orbit believes Earth is doomed, no matter what Guardians do. They advocate for deep-space exploration and hope to see humanity scattered across the entire galaxy.\",\"name\":\"Dead Orbit\",\"icon\":\"/common/destiny2_content/icons/5053c24837d4c06c7c9ccf8d0c8717fc.png\",\"hasIcon\":true},\"progressionHash\":3398051042,\"tokenValues\":{\"2959556799\":100},\"rewardItemHash\":349457197,\"rewardVendorHash\":349457197,\"vendors\":[{\"vendorHash\":3354631265,\"destinationHash\":333456177,\"backgroundImagePath\":\"img/destiny_content/factions/vendors/dead-orbit-arach-jalaal.jpg\"}],\"hash\":3398051042,\"index\":6,\"redacted\":false}"], [-599245311, "{\"displayProperties\":{\"description\":\"Keep it secret.  Keep it safe.\",\"name\":\"Classified\",\"hasIcon\":false},\"progressionHash\":0,\"rewardItemHash\":0,\"rewardVendorHash\":0,\"hash\":3695721985,\"index\":2,\"redacted\":true}"], [-98818209, "{\"displayProperties\":{\"description\":\"Sloane oversees the New Pacific Arcology on Titan, defending these precious Golden Age structures from Hive and Fallen.\",\"name\":\"Field Commander\",\"icon\":\"/common/destiny2_content/icons/878be4218aa1fabc5b8946139c5e7f0b.png\",\"hasIcon\":true},\"progressionHash\":4196149087,\"tokenValues\":{\"494493680\":100,\"461171930\":100,\"2014411539\":35},\"rewardItemHash\":2116967332,\"rewardVendorHash\":2116967332,\"vendors\":[{\"vendorHash\":1062861569,\"destinationHash\":2388758973,\"backgroundImagePath\":\"img/destiny_content/factions/vendors/titan-sloane.jpg\"}],\"hash\":4196149087,\"index\":11,\"redacted\":false}"], [-59847984, "{\"displayProperties\":{\"description\":\"Devrim Kay stands watch in the EDZ, protecting the small group of people who now call the Farm their home.\",\"name\":\"Dead Zone Scout\",\"icon\":\"/common/destiny2_content/icons/0403dd7de992e8e362764d6f7c24a36e.png\",\"hasIcon\":true},\"progressionHash\":4235119312,\"tokenValues\":{\"2640973641\":100,\"478751073\":100,\"950899352\":35},\"rewardItemHash\":2043215681,\"rewardVendorHash\":2043215681,\"vendors\":[{\"vendorHash\":396892126,\"destinationHash\":1199524104,\"backgroundImagePath\":\"img/destiny_content/factions/vendors/edz-devrim-kay.jpg\"}],\"hash\":4235119312,\"index\":8,\"redacted\":false}"], [-39383344, "{\"displayProperties\":{\"description\":\"Keep it secret.  Keep it safe.\",\"name\":\"Classified\",\"hasIcon\":false},\"progressionHash\":0,\"rewardItemHash\":0,\"rewardVendorHash\":0,\"hash\":4255583952,\"index\":1,\"redacted\":true}"], [24856709, "{\"displayProperties\":{\"description\":\"Emperor Calus of the Cabal seeks champions.\",\"name\":\"Leviathan\",\"icon\":\"/common/destiny2_content/icons/20a5bea2cf49fc39a6c0089c3d8b1629.png\",\"hasIcon\":true},\"progressionHash\":1482334108,\"tokenValues\":{\"1505278293\":100},\"rewardItemHash\":3191466416,\"rewardVendorHash\":0,\"vendors\":[{\"vendorHash\":1265988377,\"destinationHash\":333456177,\"backgroundImagePath\":\"img/destiny_content/factions/vendors/tower-leviathan-benedict-1.jpg\"}],\"hash\":24856709,\"index\":19,\"redacted\":false}"], [469305170, "{\"displayProperties\":{\"description\":\"Enigmatic and reclusive, the Nine appear to take an interest in the affairs of Guardians.\",\"name\":\"The Nine\",\"icon\":\"/common/destiny2_content/icons/bbc2a936e1088afd559b93ebe3500816.png\",\"hasIcon\":true},\"progressionHash\":3468066401,\"tokenValues\":{\"885593286\":100},\"rewardItemHash\":3496337357,\"rewardVendorHash\":3496337357,\"vendors\":[{\"vendorHash\":3190557734,\"destinationHash\":1402606356,\"backgroundImagePath\":\"img/destiny_content/factions/vendors/spire-trials-emissary-1.jpg\"}],\"hash\":469305170,\"index\":21,\"redacted\":false}"], [611314723, "{\"displayProperties\":{\"description\":\"Commander Zavala oversees the Vanguard's tactical operations and conducts regular strikes against the City's enemies.\",\"name\":\"Vanguard Tactical\",\"icon\":\"/common/destiny2_content/icons/cd6a4764552ad94823007262146fd351.png\",\"hasIcon\":true},\"progressionHash\":611314723,\"tokenValues\":{\"3899548068\":100},\"rewardItemHash\":3578462974,\"rewardVendorHash\":3578462974,\"vendors\":[{\"vendorHash\":69482069,\"destinationHash\":4188263703,\"backgroundImagePath\":\"img/destiny_content/factions/vendors/farm-strikes-zavala-0.jpg\"},{\"vendorHash\":69482069,\"destinationHash\":333456177,\"backgroundImagePath\":\"img/destiny_content/factions/vendors/strikes-commander-zavala.jpg\"}],\"hash\":611314723,\"index\":22,\"redacted\":false}"], [672350002, "{\"displayProperties\":{\"description\":\"Shipwright to the Tower, Amanda Holliday runs the Hangar like a finely tuned engine.\",\"name\":\"Chief Shipwright\",\"icon\":\"/common/destiny2_content/icons/981ed036e0f2149b15a616426ae1d79b.png\",\"hasIcon\":true},\"progressionHash\":0,\"rewardItemHash\":0,\"rewardVendorHash\":0,\"hash\":672350002,\"index\":20,\"redacted\":false}"], [697030790, "{\"displayProperties\":{\"description\":\"The Crucible is a live-fire training exercise where Guardians train and compete.\",\"name\":\"The Crucible\",\"icon\":\"/common/destiny2_content/icons/e84bd523ff13eb916a92c241275f4ce9.png\",\"hasIcon\":true},\"progressionHash\":697030790,\"tokenValues\":{\"183980811\":100},\"rewardItemHash\":1368565477,\"rewardVendorHash\":1368565477,\"vendors\":[{\"vendorHash\":3603221665,\"destinationHash\":4188263703,\"backgroundImagePath\":\"img/destiny_content/factions/vendors/farm-crucible-shaxx-0.jpg\"},{\"vendorHash\":3603221665,\"destinationHash\":4188263703,\"backgroundImagePath\":\"img/destiny_content/factions/vendors/farm-crucible-shaxx-0.jpg\"},{\"vendorHash\":3603221665,\"destinationHash\":333456177,\"backgroundImagePath\":\"img/destiny_content/factions/vendors/crucible-lord-shaxx.jpg\"}],\"hash\":697030790,\"index\":4,\"redacted\":false}"], [828982195, "{\"displayProperties\":{\"description\":\"Asher Mir resides on Io, researching the Vex and keeping an eye over the last place the Traveler touched.\",\"name\":\"Fragmented Researcher\",\"icon\":\"/common/destiny2_content/icons/925b5bc7e8fb0989fbb54bcc961f3c57.png\",\"hasIcon\":true},\"progressionHash\":828982195,\"tokenValues\":{\"3825769808\":100,\"3756389242\":100,\"1305274547\":35},\"rewardItemHash\":3565220806,\"rewardVendorHash\":3565220806,\"vendors\":[{\"vendorHash\":3982706173,\"destinationHash\":2218917881,\"backgroundImagePath\":\"img/destiny_content/factions/vendors/io-asher-mir.jpg\"}],\"hash\":828982195,\"index\":7,\"redacted\":false}"], [952405032, "{\"displayProperties\":{\"description\":\"Keep it secret.  Keep it safe.\",\"name\":\"Classified\",\"hasIcon\":false},\"progressionHash\":0,\"rewardItemHash\":0,\"rewardVendorHash\":0,\"hash\":952405032,\"index\":0,\"redacted\":true}"], [1021210278, "{\"displayProperties\":{\"description\":\"Gunsmiths maintain the Guardian arsenal, procuring and fixing the weapons Guardians use in their travels.\",\"name\":\"Gunsmith\",\"icon\":\"/common/destiny2_content/icons/0c731069843c47848bf8c1849ee065ef.png\",\"hasIcon\":true},\"progressionHash\":1021210278,\"tokenValues\":{\"685157383\":75,\"685157381\":25},\"rewardItemHash\":3531414277,\"rewardVendorHash\":3531414277,\"vendors\":[{\"vendorHash\":3466008634,\"destinationHash\":4188263703,\"backgroundImagePath\":\"img/destiny_content/factions/vendors/farm-gunsmith-arcite-0.jpg\"},{\"vendorHash\":3466008634,\"destinationHash\":4188263703,\"backgroundImagePath\":\"img/destiny_content/factions/vendors/farm-gunsmith-arcite-0.jpg\"},{\"vendorHash\":672118013,\"destinationHash\":333456177,\"backgroundImagePath\":\"img/destiny_content/factions/vendors/gunsmith-banshee-44.jpg\"}],\"hash\":1021210278,\"index\":12,\"redacted\":false}"], [1357903713, "{\"displayProperties\":{\"description\":\"Enigmatic and reclusive, the Nine appear to take an interest in the affairs of Guardians.\",\"name\":\"The Nine\",\"icon\":\"/common/destiny2_content/icons/bbc2a936e1088afd559b93ebe3500816.png\",\"hasIcon\":true},\"progressionHash\":0,\"rewardItemHash\":0,\"rewardVendorHash\":0,\"hash\":1357903713,\"index\":17,\"redacted\":false}"], [1393733616, "{\"displayProperties\":{\"description\":\"Tess Everis sells curios and accessories from her stylish boutique in the Tower.\",\"name\":\"Eververse\",\"icon\":\"/common/destiny2_content/icons/3293b713a8b1eb944d8d1c72008fb440.png\",\"hasIcon\":true},\"progressionHash\":0,\"rewardItemHash\":0,\"rewardVendorHash\":0,\"hash\":1393733616,\"index\":9,\"redacted\":false}"], [1647279527, "{\"displayProperties\":{\"description\":\"Skilled historians and cryptographers, the Cryptarchs are always happy to decrypt a challenging engram for Guardians.\",\"name\":\"Cryptarchs\",\"icon\":\"/common/destiny2_content/icons/3293b713a8b1eb944d8d1c72008fb440.png\",\"hasIcon\":true},\"progressionHash\":0,\"rewardItemHash\":0,\"rewardVendorHash\":0,\"hash\":1647279527,\"index\":5,\"redacted\":false}"], [1660497607, "{\"displayProperties\":{\"description\":\"A Golden Age AI marooned on  Nessus, Failsafe stands watch over the wreckage of her ship.\",\"name\":\"Exodus Black AI\",\"icon\":\"/common/destiny2_content/icons/047270ee337c3131c8370d28325829e4.png\",\"hasIcon\":true},\"progressionHash\":1660497607,\"tokenValues\":{\"3201839676\":100,\"2949414982\":100,\"3487922223\":35},\"rewardItemHash\":3876745998,\"rewardVendorHash\":468122550,\"vendors\":[{\"vendorHash\":1576276905,\"destinationHash\":126924919,\"backgroundImagePath\":\"img/destiny_content/factions/vendors/nessus-failsafe.jpg\"}],\"hash\":1660497607,\"index\":15,\"redacted\":false}"], [1714509342, "{\"displayProperties\":{\"description\":\"Future War Cult believes that war is not only inevitable, but the one true meaning of life.\",\"name\":\"Future War Cult\",\"icon\":\"/common/destiny2_content/icons/9b5633acd3b871ad7bb63ec682063300.png\",\"hasIcon\":true},\"progressionHash\":1714509342,\"tokenValues\":{\"1270564331\":100},\"rewardItemHash\":1744720571,\"rewardVendorHash\":1744720571,\"vendors\":[{\"vendorHash\":2260557667,\"destinationHash\":333456177,\"backgroundImagePath\":\"img/destiny_content/factions/vendors/future-war-cult-lakshmi-2.jpg\"}],\"hash\":1714509342,\"index\":10,\"redacted\":false}"], [1761642340, "{\"displayProperties\":{\"description\":\"The Iron Banner is a Crucible tournament held to honor long-lost heroes.\",\"name\":\"Iron Banner\",\"icon\":\"/common/destiny2_content/icons/d964c13607d7d24ef7ba6aa22a27b82d.png\",\"hasIcon\":true},\"progressionHash\":1761642340,\"tokenValues\":{\"1873857625\":100},\"rewardItemHash\":1762796941,\"rewardVendorHash\":1762796941,\"vendors\":[{\"vendorHash\":895295461,\"destinationHash\":333456177,\"backgroundImagePath\":\"img/destiny_content/factions/vendors/tower-iron-banner-saladin-1.jpg\"}],\"hash\":1761642340,\"index\":14,\"redacted\":false}"], [1838583129, "{\"displayProperties\":{\"description\":\"The postmaster handles deliveries destined for residents of the Tower, including lost items.\",\"name\":\"Postmaster\",\"icon\":\"/common/destiny2_content/icons/3293b713a8b1eb944d8d1c72008fb440.png\",\"hasIcon\":true},\"progressionHash\":0,\"rewardItemHash\":0,\"rewardVendorHash\":0,\"hash\":1838583129,\"index\":18,\"redacted\":false}"], [2105209711, "{\"displayProperties\":{\"description\":\"New Monarchy believes the City\u2014and all of humanity\u2014needs to unite behind a single powerful ruler.\",\"name\":\"New Monarchy\",\"icon\":\"/common/destiny2_content/icons/f3e37619475a90091b86946db22fed38.png\",\"hasIcon\":true},\"progressionHash\":2105209711,\"tokenValues\":{\"2270228604\":100},\"rewardItemHash\":4110173410,\"rewardVendorHash\":4110173410,\"vendors\":[{\"vendorHash\":3819664660,\"destinationHash\":333456177,\"backgroundImagePath\":\"img/destiny_content/factions/vendors/new-monarchy-executor-hideo.jpg\"}],\"hash\":2105209711,\"index\":16,\"redacted\":false}"]]